uzemszunet/__init__.py
uzemszunet/__main__.py
uzemszunet/config.py
uzemszunet/emasz.py
uzemszunet/eon.py
uzemszunet/exceptions.py
uzemszunet/jinjaext.py
uzemszunet/mindigtv.py
uzemszunet/sendmail.py
uzemszunet/utils.py
uzemszunet/uzemszunet.cfg
uzemszunet/templates/base.jinja
uzemszunet/templates/egyszeru_lista.jinja
uzemszunet/templates/heartbeat.jinja
uzemszunet/templates/rendezett_lista.jinja
uzemszunet-0.0.5.dist-info/LICENSE.md
uzemszunet-0.0.5.dist-info/METADATA
uzemszunet-0.0.5.dist-info/WHEEL
uzemszunet-0.0.5.dist-info/entry_points.txt
uzemszunet-0.0.5.dist-info/top_level.txt
uzemszunet-0.0.5.dist-info/RECORD
