Metadata-Version: 2.1
Name: uzemszunet
Version: 0.0.5
Summary: Üzemszünetek lekérdezése
Home-page: https://github.com/husudosu/uzemszunet
Author: Ferenc Nánási
Author-email: husudosu94@gmail.com
License: UNKNOWN
Platform: UNKNOWN
Classifier: Development Status :: 3 - Alpha
Classifier: Environment :: Console
Classifier: License :: OSI Approved :: MIT License
Classifier: Intended Audience :: System Administrators
Classifier: Natural Language :: Hungarian
Classifier: Programming Language :: Python :: 3.6
Classifier: Programming Language :: Python :: 3.7
Classifier: Programming Language :: Python :: 3.8
Classifier: Topic :: Communications :: Email
Classifier: Topic :: Utilities
Requires-Python: >=3.6
Requires-Dist: jinja2
Requires-Dist: pandas (==1.1.5)
Requires-Dist: requests
Requires-Dist: xlrd (==1.2.0)
